petpropy/__init__.py
petpropy/_tools/__init__.py
petpropy/_tools/tools.py
petpropy/gas/__init__.py
petpropy/gas/gas_compressibility.py
petpropy/gas/gas_compressibility_factor.py
petpropy/gas/gas_density.py
petpropy/gas/gas_viscosity.py
petpropy/gas/gas_volumetric_factor.py
petpropy/gas/pseudocritical_properties_gas.py
petpropy/gas/specific_gravity_gas.py
petpropy/gas/weight_molecular_gas.py
petpropy/oil/__init__.py
petpropy/oil/bubble_pressure.py
petpropy/oil/gas_oil_interfacial_tension.py
petpropy/oil/oil_compressibility.py
petpropy/oil/oil_density.py
petpropy/oil/oil_viscosity.py
petpropy/oil/oil_volumetric_factor.py
petpropy/oil/solution_gas_oil_ratio.py
petpropy/oil/specific_gravity_oil.py
petpropy/oil/total_volumetric_factor.py
petpropy/water/__init__.py
petpropy/water/gas_water_interfacial_tension.py
petpropy/water/solution_gas_water_ratio.py
petpropy/water/water_compressibility.py
petpropy/water/water_density.py
petpropy/water/water_viscosity.py
petpropy/water/water_volumetric_factor.py
petpropy-1.0.4.dist-info/LICENSE
petpropy-1.0.4.dist-info/METADATA
petpropy-1.0.4.dist-info/WHEEL
petpropy-1.0.4.dist-info/top_level.txt
petpropy-1.0.4.dist-info/RECORD
