Metadata-Version: 2.1
Name: petpropy
Version: 1.0.4
Summary: Calculator package of physical properties of Gas, Oil, and Water in Python.
Author: Ever J. Ramos I.
License:                    GNU LESSER GENERAL PUBLIC LICENSE
Project-URL: Homepage, https://github.com/EverJRamosI/petpropy
Project-URL: Bug Reports, https://github.com/EverJRamosI/petpropy/issues
Project-URL: Contact, https://www.linkedin.com/in/everjramosi/
Keywords: petroleum,chemical,petroleum-engineering,chemical-engineering,oil-and-gas
Classifier: Programming Language :: Python :: 3
Classifier: License :: OSI Approved :: GNU Lesser General Public License v3 (LGPLv3)
Classifier: Operating System :: OS Independent
Requires-Python: >=3.10
License-File: LICENSE
Requires-Dist: numpy
Requires-Dist: pandas
